<?xml version="1.0" encoding="UTF-8"?>
<as:AppSchemaDataAccess xmlns:as="http://www.geotools.org/app-schema" xmlns:xsi="http://www.w3.org/2001/XMLSchema-instance"
    xsi:schemaLocation="http://www.geotools.org/app-schema AppSchemaDataAccess.xsd">
	<namespaces>
		<Namespace><prefix>gml</prefix><uri>http://www.opengis.net/gml/3.2</uri></Namespace>
		<Namespace><prefix>om</prefix><uri>http://www.opengis.net/om/2.0</uri></Namespace>
		<Namespace><prefix>sam</prefix><uri>http://www.opengis.net/sampling/2.0</uri></Namespace>
		<Namespace><prefix>sams</prefix><uri>http://www.opengis.net/samplingSpatial/2.0</uri></Namespace>
		<Namespace><prefix>xlink</prefix><uri>http://www.w3.org/1999/xlink</uri></Namespace>
		<Namespace><prefix>xsi</prefix><uri>http://www.w3.org/2001/XMLSchema-instance</uri></Namespace>
	</namespaces>
	<sourceDataStores>
		<DataStore>
			<id>datastore</id>
			<parameters>
				<Parameter><name>dbtype</name><value>${eodp.dbtype}</value></Parameter>
				<!--Parameter><name>jndiReferenceName</name><value>${eodp.jndi}</value></Parameter-->
				<Parameter><name>host</name><value>${eodp.host}</value></Parameter>
				<Parameter><name>port</name><value>${eodp.port}</value></Parameter>
				<Parameter><name>database</name><value>${eodp.database}</value></Parameter>
				<Parameter><name>user</name><value>${eodp.user}</value></Parameter>
				<Parameter><name>passwd</name><value>${eodp.passwd}</value></Parameter>
				<Parameter><name>schema</name><value>${eodp.schema}</value></Parameter>
				<Parameter><name>Expose primary keys</name><value>true</value></Parameter>
			</parameters>
		</DataStore>
	</sourceDataStores>
	<targetTypes>
		<FeatureType>
		  <schemaUri>http://schemas.opengis.net/samplingSpatial/2.0/spatialSamplingFeature.xsd</schemaUri>
		  <schemaUri>http://schemas.opengis.net/om/2.0/observation.xsd</schemaUri>
		</FeatureType>
	</targetTypes>
	<typeMappings>
		<FeatureTypeMapping>
			<sourceDataStore>datastore</sourceDataStore>
			<sourceType>samplingfeature</sourceType>
			<targetElement>sams:SF_SpatialSamplingFeature</targetElement>
			<attributeMappings>
				<AttributeMapping>
					<targetAttribute>sams:SF_SpatialSamplingFeature</targetAttribute>
					<idExpression><OCQL>gmlid</OCQL></idExpression>
				</AttributeMapping>
				<AttributeMapping>
					<targetAttribute>gml:description</targetAttribute>
					<sourceExpression><OCQL>samplingfeaturedescription</OCQL></sourceExpression>
				</AttributeMapping>
				<AttributeMapping>
					<targetAttribute>gml:identifier</targetAttribute>
					<sourceExpression><OCQL>gmlidentifier</OCQL></sourceExpression>	
					<ClientProperty><name>codeSpace</name><value>'${lcr.codespace}'</value></ClientProperty>	
				</AttributeMapping>
				<AttributeMapping>
					<targetAttribute>gml:name</targetAttribute>
					<sourceExpression><OCQL>samplingfeaturename</OCQL></sourceExpression>	
					<ClientProperty><name>codeSpace</name><value>'${lcr.codespace}'</value></ClientProperty>	
				</AttributeMapping>
				<AttributeMapping>
					<targetAttribute>gml:name</targetAttribute>
					<sourceExpression><OCQL>strConCat('MS.SI.', samplingfeatureid)</OCQL></sourceExpression>	
					<ClientProperty><name>codeSpace</name><value>'http://someotherparty.example.org.nz'</value></ClientProperty>	
				</AttributeMapping>
				<AttributeMapping>
					<targetAttribute>sam:type</targetAttribute>
					<ClientProperty><name>xlink:href</name><value>samplingfeaturetypeuri</value></ClientProperty>
				</AttributeMapping>
				<AttributeMapping>
					<targetAttribute>sam:sampledFeature</targetAttribute>
					<ClientProperty><name>xsi:nil</name><value>'true'</value></ClientProperty>
					<ClientProperty><name>nilReason</name><value>'missing'</value></ClientProperty>					
				</AttributeMapping>
				<AttributeMapping>
					<targetAttribute>sam:relatedObservation</targetAttribute>
					<sourceExpression><OCQL>samplingfeatureid</OCQL><linkElement>_om_OM_Observation</linkElement><linkField>FEATURE_LINK</linkField></sourceExpression>
					<isMultiple>true</isMultiple>
				</AttributeMapping>
				<AttributeMapping>
					<targetAttribute>sams:shape/gml:Point</targetAttribute>
					<!--=== Geoserver should have automagically detected that the geometry was a point, but didn't - hence explicit ===
                        === sams:shape/gml:Point target. May be something awry with my PostGIS 2.0 set-up (?).                      ===-->
					<idExpression><OCQL>strConcat('sams.shape.', samplingfeatureid)</OCQL></idExpression>
					<sourceExpression><OCQL>shape</OCQL></sourceExpression>							
				</AttributeMapping>	
			</attributeMappings>
		</FeatureTypeMapping>
		<FeatureTypeMapping>
			<mappingName>_om_OM_Observation</mappingName>
			<!--=== Using a local om:OM_Observation mapping as the om:featureOfInterest mapping here differs (xlink:href) from the one used by ===
                === the om:OM_Observation published as a feature type (inline sams:SF_SpatialSamplingFeature).                                 ===-->
			<sourceDataStore>datastore</sourceDataStore>
			<sourceType>observationdiscovery</sourceType>
			<targetElement>om:OM_Observation</targetElement>
			<attributeMappings>
				<AttributeMapping>
					<targetAttribute>om:OM_Observation</targetAttribute>
					<idExpression><OCQL>gmlid</OCQL></idExpression>
				</AttributeMapping>
				<AttributeMapping>
					<targetAttribute>gml:identifier</targetAttribute>
					<sourceExpression><OCQL>gmlidentifier</OCQL></sourceExpression>	
					<ClientProperty><name>codeSpace</name><value>'${lcr.codespace}'</value></ClientProperty>	
				</AttributeMapping>
				<AttributeMapping>
					<targetAttribute>om:type</targetAttribute>
					<ClientProperty><name>xlink:href</name><value>observationtypeuri</value></ClientProperty>
				</AttributeMapping>
				<AttributeMapping>
					<targetAttribute>om:phenomenonTime</targetAttribute>
					<!--=== Can reuse the _om_phenomenonTime mapping created for the published om:OM_Observation configuration. ===-->
					<sourceExpression><linkElement>_om_phenomenonTime</linkElement></sourceExpression>
				</AttributeMapping>
				<AttributeMapping>
					<targetAttribute>om:resultTime</targetAttribute>
					<!--=== Can reuse the _om_resultTime mapping created for the published om:OM_Observation configuration. ===-->
					<sourceExpression><linkElement>_om_resultTime</linkElement></sourceExpression>
				</AttributeMapping>
				<AttributeMapping>
					<targetAttribute>om:validTime</targetAttribute>
					<ClientProperty><name>xlink:href</name><value>'${nil.inapplicable}'</value></ClientProperty>
				</AttributeMapping>
				<AttributeMapping>
					<targetAttribute>om:procedure</targetAttribute>
					<ClientProperty><name>xlink:href</name><value>procedureuri</value></ClientProperty>
				</AttributeMapping>
				<AttributeMapping>
					<targetAttribute>om:observedProperty</targetAttribute>
					<ClientProperty><name>xlink:href</name><value>observedpropertyuri</value></ClientProperty>
				</AttributeMapping>
				<AttributeMapping>
					<targetAttribute>om:featureOfInterest</targetAttribute>
					<ClientProperty><name>xlink:href</name><value>samplingfeatureuri</value></ClientProperty>
				</AttributeMapping>
				<AttributeMapping>
					<targetAttribute>om:resultQuality</targetAttribute>
					<ClientProperty><name>xlink:href</name><value>'${nil.inapplicable}'</value></ClientProperty>
				</AttributeMapping>				
				<AttributeMapping>
					<targetAttribute>om:result</targetAttribute>
					<ClientProperty><name>xlink:href</name><value>'${nil.withheld}'</value></ClientProperty>
				</AttributeMapping>
				<AttributeMapping>
					<targetAttribute>FEATURE_LINK</targetAttribute>
					<sourceExpression><OCQL>samplingfeatureid</OCQL></sourceExpression>
				</AttributeMapping>
			</attributeMappings>
		</FeatureTypeMapping>-->
	</typeMappings>
</as:AppSchemaDataAccess>